{
    "BearsBearsBears.json": ["Bears! Bears! Bears!"],
    "CeldirasCompendiumOfKnowledge.json": ["Celdira's Compendium of Knowledge"],
    "WitheringFury.json": ["Withering Fury"],
    "RagingFlames.json": ["Raging Flames"],
    "WilbunsWordsOfWeirdness.json": ["Wilbun' Words of Weirdness"],
    "OrreanAdventuringGuide.json": ["Orrean Adventuring Guide"],
    "ElgyrsDraconicMenagery.json": ["Elgyr's Draconic Menagery"],
    "BartholomeusTomeOfBattle.json": ["Bartholomeus' Tome of Battle"],
    "CriticalRoll.json": ["Critical Roll"],
    "MartialRanger.json": ["Martial Ranger"],
    "OrdisJournalOfSeafaring.json": ["Ordi's Journal of Seafaring"]
}